PySiddhi4/SiddhiLoader.py
PySiddhi4/__init__.py
PySiddhi4/DataTypes/DataWrapper.py
PySiddhi4/DataTypes/DoubleType.py
PySiddhi4/DataTypes/LongType.py
PySiddhi4/DataTypes/__init__.py
PySiddhi4/core/SiddhiAppRuntime.py
PySiddhi4/core/SiddhiManager.py
PySiddhi4/core/__init__.py
PySiddhi4/core/debugger/SiddhiDebugger.py
PySiddhi4/core/debugger/SiddhiDebuggerCallback.py
PySiddhi4/core/debugger/__init__.py
PySiddhi4/core/event/ComplexEvent.py
PySiddhi4/core/event/Event.py
PySiddhi4/core/event/__init__.py
PySiddhi4/core/query/__init__.py
PySiddhi4/core/query/output/__init__.py
PySiddhi4/core/query/output/callback/QueryCallback.py
PySiddhi4/core/query/output/callback/__init__.py
PySiddhi4/core/stream/__init__.py
PySiddhi4/core/stream/input/InputHandler.py
PySiddhi4/core/stream/input/__init__.py
PySiddhi4/core/stream/output/StreamCallback.py
PySiddhi4/core/stream/output/__init__.py
PySiddhi4/core/util/EventPrinter.py
PySiddhi4/core/util/__init__.py
PySiddhi4/sp/SPClient.py
PySiddhi4/sp/__Util.py
PySiddhi4/sp/__init__.py
PySiddhi4/sp/EventSimulator/AttributeConfiguration.py
PySiddhi4/sp/EventSimulator/EventSimulatorClient.py
PySiddhi4/sp/EventSimulator/FeedSimulationConfiguration.py
PySiddhi4/sp/EventSimulator/SimulationProperties.py
PySiddhi4/sp/EventSimulator/SimulationSource.py
PySiddhi4/sp/EventSimulator/SingleSimulationConfiguration.py
PySiddhi4/sp/EventSimulator/__init__.py
PySiddhi4/sp/ObjectMapping/APIObject.py
PySiddhi4/sp/ObjectMapping/FieldMapping.py
PySiddhi4/sp/ObjectMapping/__init__.py
PySiddhi4/sp/SiddhiAppManagement/SiddhiAppManagementClient.py
PySiddhi4/sp/SiddhiAppManagement/__init__.py
PySiddhi4/sp/__Communication/RestClient.py
PySiddhi4/sp/__Communication/__init__.py
__PySiddhi4Proxy/liborg_wso2_siddhi_pythonapi_threadfix_pythreadfix.so
__PySiddhi4Proxy/target/siddhi-python-api-proxy-4-1.1.0.jar
__PySiddhi4Proxy/target/lib/accessors-smart-1.1.jar
__PySiddhi4Proxy/target/lib/antlr4-runtime-4.5.1.jar
__PySiddhi4Proxy/target/lib/asm-5.0.3.jar
PySiddhi4-1.1.0.dist-info/LICENSE.txt
PySiddhi4-1.1.0.dist-info/METADATA
PySiddhi4-1.1.0.dist-info/WHEEL
PySiddhi4-1.1.0.dist-info/top_level.txt
PySiddhi4-1.1.0.dist-info/RECORD
