Metadata-Version: 2.1
Name: PySiddhi4
Version: 1.1.0
Summary: Python wrapper for `Siddhi 4.x.x`.
Home-page: https://github.com/wso2/PySiddhi
Author: WSO2
Author-email: dev@wso2.org
License: Apache2
Platform: UNKNOWN
Classifier: Development Status :: 5 - Production/Stable
Classifier: Intended Audience :: Developers
Classifier: License :: OSI Approved :: Apache Software License
Classifier: Natural Language :: English
Classifier: Operating System :: Microsoft :: Windows
Classifier: Operating System :: POSIX :: Linux
Classifier: Operating System :: MacOS
Classifier: Programming Language :: Python :: 2.7
Classifier: Programming Language :: Python :: 3.3
Classifier: Programming Language :: Python :: 3.4
Classifier: Programming Language :: Python :: 3.5
Classifier: Programming Language :: Python :: 3.6
Classifier: Programming Language :: Python :: 3.7
Classifier: Topic :: Software Development :: Libraries :: Java Libraries
Requires-Python: >=2.7, ~=3.5
Requires-Dist: requests
Requires-Dist: pyjnius
Requires-Dist: future
Requires-Dist: enum34 ; python_version < "4"
